CACHING.rst
CHANGELOG.md
INSTALLATION.rst
LICENSE.md
MANIFEST.in
README.md
pyphi_config.yml
redis.conf
setup.cfg
setup.py
pyphinb/__about__.py
pyphinb/__init__.py
pyphinb/actual.py
pyphinb/cache.py
pyphinb/conf.py
pyphinb/connectivity.py
pyphinb/constants.py
pyphinb/convert.py
pyphinb/db.py
pyphinb/direction.py
pyphinb/distance.py
pyphinb/distribution.py
pyphinb/examples.py
pyphinb/exceptions.py
pyphinb/jsonify.py
pyphinb/labels.py
pyphinb/log.py
pyphinb/macro.py
pyphinb/memory.py
pyphinb/network.py
pyphinb/network_nb.py
pyphinb/node.py
pyphinb/partition.py
pyphinb/registry.py
pyphinb/subsystem.py
pyphinb/subsystem_nb.py
pyphinb/timescale.py
pyphinb/tpm.py
pyphinb/utils.py
pyphinb/validate.py
pyphinb.egg-info/PKG-INFO
pyphinb.egg-info/SOURCES.txt
pyphinb.egg-info/dependency_links.txt
pyphinb.egg-info/not-zip-safe
pyphinb.egg-info/requires.txt
pyphinb.egg-info/top_level.txt
pyphinb/compute/__init__.py
pyphinb/compute/distance.py
pyphinb/compute/network.py
pyphinb/compute/nonbinary.py
pyphinb/compute/parallel.py
pyphinb/compute/subsystem.py
pyphinb/data/base.npy
pyphinb/data/distance_matrices.npy
pyphinb/data/labels.npy
pyphinb/data/hamming_matrices/0.npy
pyphinb/data/hamming_matrices/1.npy
pyphinb/data/hamming_matrices/2.npy
pyphinb/data/hamming_matrices/3.npy
pyphinb/data/hamming_matrices/4.npy
pyphinb/data/hamming_matrices/5.npy
pyphinb/data/hamming_matrices/6.npy
pyphinb/data/hamming_matrices/7.npy
pyphinb/data/hamming_matrices/8.npy
pyphinb/data/hamming_matrices/9.npy
pyphinb/data/partition_lists/0.npy
pyphinb/data/partition_lists/1.npy
pyphinb/data/partition_lists/2.npy
pyphinb/data/partition_lists/3.npy
pyphinb/data/partition_lists/4.npy
pyphinb/data/partition_lists/5.npy
pyphinb/data/partition_lists/6.npy
pyphinb/data/partition_lists/7.npy
pyphinb/data/partition_lists/8.npy
pyphinb/data/partition_lists/9.npy
pyphinb/models/__init__.py
pyphinb/models/actual_causation.py
pyphinb/models/cmp.py
pyphinb/models/cuts.py
pyphinb/models/fmt.py
pyphinb/models/mechanism.py
pyphinb/models/subsystem.py
test/test_actual.py
test/test_big_phi.py
test/test_cache.py
test/test_ces.py
test/test_concept_style_cuts.py
test/test_config.py
